{
    "0": {
        "answer": {
            "end_time": 0,
            "start_time": "2021-12-03 20:02:52.664854",
            "steps": [
                {
                    "part_id": [
                        0,
                        0
                    ],
                    "state": "waiting to be cooked",
                    "step": 0,
                    "time_stamp": "2021-12-03 20:02:52.664854",
                    "worker_id": 0
                },
                {
                    "part_id": [
                        0,
                        1
                    ],
                    "state": "waiting to be cooked",
                    "step": 1,
                    "time_stamp": "2021-12-03 20:02:52.664854",
                    "worker_id": 0
                },
                {
                    "part_id": [
                        0,
                        2
                    ],
                    "state": "waiting to be cooked",
                    "step": 2,
                    "time_stamp": "2021-12-03 20:02:52.664854",
                    "worker_id": 0
                },
                {
                    "part_id": [
                        0,
                        3
                    ],
                    "state": "waiting to be cooked",
                    "step": 3,
                    "time_stamp": "2021-12-03 20:02:52.664854",
                    "worker_id": 0
                },
                {
                    "part_id": [
                        0,
                        1
                    ],
                    "state": "cooking stack #0(0) of 5.0 tacos",
                    "step": 4,
                    "time_stamp": "2021-12-03 20:02:52.680500",
                    "worker_id": 0
                },
                {
                    "part_id": [
                        0,
                        0
                    ],
                    "state": "Suborder 0 arrived at taquero Jerry",
                    "step": 5,
                    "time_stamp": "2021-12-03 20:02:52.680500",
                    "worker_id": 3
                },
                {
                    "part_id": [
                        0,
                        0
                    ],
                    "state": "cooking stack #0(0) of 2.0 tacos",
                    "step": 6,
                    "time_stamp": "2021-12-03 20:02:52.680500",
                    "worker_id": 3
                },
                {
                    "part_id": [
                        0,
                        2
                    ],
                    "state": "Suborder 2 arrived at taquero Jerry",
                    "step": 7,
                    "time_stamp": "2021-12-03 20:02:55.685113",
                    "worker_id": 3
                },
                {
                    "part_id": [
                        0,
                        0
                    ],
                    "state": "Stack#0(0) complete",
                    "step": 8,
                    "time_stamp": "2021-12-03 20:02:57.770149",
                    "worker_id": 3
                },
                {
                    "part_id": [
                        0,
                        0
                    ],
                    "state": "Switching to order 3",
                    "step": 9,
                    "time_stamp": "2021-12-03 20:02:57.770149",
                    "worker_id": 3
                },
                {
                    "part_id": [
                        0,
                        3
                    ],
                    "state": "Suborder 3 arrived at taquero Jerry",
                    "step": 10,
                    "time_stamp": "2021-12-03 20:02:58.701953",
                    "worker_id": 3
                },
                {
                    "part_id": [
                        0,
                        1
                    ],
                    "state": "Stack#0(0) complete",
                    "step": 11,
                    "time_stamp": "2021-12-03 20:03:02.788885",
                    "worker_id": 0
                },
                {
                    "part_id": [
                        0,
                        1
                    ],
                    "state": "Switching to order 6",
                    "step": 12,
                    "time_stamp": "2021-12-03 20:03:02.788885",
                    "worker_id": 0
                },
                {
                    "part_id": [
                        0,
                        1
                    ],
                    "state": "cooking stack #1(1) of 5.0 tacos",
                    "step": 13,
                    "time_stamp": "2021-12-03 20:03:07.893371",
                    "worker_id": 0
                },
                {
                    "part_id": [
                        0,
                        0
                    ],
                    "state": "cooking stack #1(1) of 5.0 tacos",
                    "step": 14,
                    "time_stamp": "2021-12-03 20:03:07.908993",
                    "worker_id": 3
                },
                {
                    "part_id": [
                        0,
                        1
                    ],
                    "state": "Stack#1(1) complete",
                    "step": 15,
                    "time_stamp": "2021-12-03 20:03:17.968787",
                    "worker_id": 0
                },
                {
                    "part_id": [
                        0,
                        1
                    ],
                    "state": "Switching to order 2",
                    "step": 16,
                    "time_stamp": "2021-12-03 20:03:17.968787",
                    "worker_id": 0
                },
                {
                    "part_id": [
                        0,
                        0
                    ],
                    "state": "Stack#1(1) complete",
                    "step": 17,
                    "time_stamp": "2021-12-03 20:03:20.523091",
                    "worker_id": 3
                },
                {
                    "part_id": [
                        0,
                        2
                    ],
                    "state": "cooking stack #0(4) of 5 tacos",
                    "step": 18,
                    "time_stamp": "2021-12-03 20:03:20.523234",
                    "worker_id": 3
                },
                {
                    "part_id": [
                        0,
                        0
                    ],
                    "state": "Switching to order 2",
                    "step": 19,
                    "time_stamp": "2021-12-03 20:03:20.523234",
                    "worker_id": 3
                },
                {
                    "part_id": [
                        0,
                        1
                    ],
                    "state": "cooking stack #2(2) of 5.0 tacos",
                    "step": 20,
                    "time_stamp": "2021-12-03 20:03:28.067478",
                    "worker_id": 0
                },
                {
                    "part_id": [
                        0,
                        2
                    ],
                    "state": "Stack#0(4) complete",
                    "step": 21,
                    "time_stamp": "2021-12-03 20:03:30.682949",
                    "worker_id": 3
                },
                {
                    "part_id": [
                        0,
                        2
                    ],
                    "state": "Suborder 2 complete",
                    "step": 22,
                    "time_stamp": "2021-12-03 20:03:30.682949",
                    "worker_id": 3
                },
                {
                    "part_id": [
                        0,
                        0
                    ],
                    "state": "cooking stack #2(2) of 5.0 tacos",
                    "step": 23,
                    "time_stamp": "2021-12-03 20:03:30.682949",
                    "worker_id": 3
                },
                {
                    "part_id": [
                        0,
                        0
                    ],
                    "state": "Order 0 complete",
                    "step": 24,
                    "time_stamp": "2021-12-03 20:03:32.083969",
                    "worker_id": 0
                },
                {
                    "part_id": [
                        0,
                        1
                    ],
                    "state": "Stack#2(2) complete",
                    "step": 25,
                    "time_stamp": "2021-12-03 20:03:38.216887",
                    "worker_id": 0
                },
                {
                    "part_id": [
                        0,
                        1
                    ],
                    "state": "Switching to order 2",
                    "step": 26,
                    "time_stamp": "2021-12-03 20:03:38.216887",
                    "worker_id": 0
                },
                {
                    "part_id": [
                        0,
                        0
                    ],
                    "state": "Stack#2(2) complete",
                    "step": 27,
                    "time_stamp": "2021-12-03 20:03:43.398601",
                    "worker_id": 3
                },
                {
                    "part_id": [
                        0,
                        0
                    ],
                    "state": "Switching to order 5",
                    "step": 28,
                    "time_stamp": "2021-12-03 20:03:43.398601",
                    "worker_id": 3
                },
                {
                    "part_id": [
                        0,
                        1
                    ],
                    "state": "cooking stack #3(3) of 5.0 tacos",
                    "step": 29,
                    "time_stamp": "2021-12-03 20:03:48.355787",
                    "worker_id": 0
                },
                {
                    "part_id": [
                        0,
                        0
                    ],
                    "state": "cooking stack #3(3) of 5.0 tacos",
                    "step": 30,
                    "time_stamp": "2021-12-03 20:03:55.569672",
                    "worker_id": 3
                },
                {
                    "part_id": [
                        0,
                        1
                    ],
                    "state": "fan activation at Omar's station",
                    "step": 31,
                    "time_stamp": "2021-12-03 20:03:56.562327",
                    "worker_id": 0
                },
                {
                    "part_id": [
                        0,
                        1
                    ],
                    "state": "Stack#3(3) complete",
                    "step": 32,
                    "time_stamp": "2021-12-03 20:03:58.542336",
                    "worker_id": 0
                },
                {
                    "part_id": [
                        0,
                        1
                    ],
                    "state": "Suborder 1 complete",
                    "step": 33,
                    "time_stamp": "2021-12-03 20:03:58.542336",
                    "worker_id": 0
                },
                {
                    "part_id": [
                        0,
                        1
                    ],
                    "state": "Switching to order 2",
                    "step": 34,
                    "time_stamp": "2021-12-03 20:03:58.542336",
                    "worker_id": 0
                },
                {
                    "part_id": [
                        0,
                        0
                    ],
                    "state": "Stack#3(3) complete",
                    "step": 35,
                    "time_stamp": "2021-12-03 20:04:08.235418",
                    "worker_id": 3
                },
                {
                    "part_id": [
                        0,
                        0
                    ],
                    "state": "Suborder 0 complete",
                    "step": 36,
                    "time_stamp": "2021-12-03 20:04:08.235418",
                    "worker_id": 3
                },
                {
                    "part_id": [
                        0,
                        0
                    ],
                    "state": "Order 0 complete",
                    "step": 37,
                    "time_stamp": "2021-12-03 20:04:08.453702",
                    "worker_id": 0
                },
                {
                    "part_id": [
                        0,
                        3
                    ],
                    "state": "cooking stack #0(7) of 2 tacos",
                    "step": 38,
                    "time_stamp": "2021-12-03 20:04:24.439527",
                    "worker_id": 3
                },
                {
                    "part_id": [
                        0,
                        3
                    ],
                    "state": "Stack#0(7) complete",
                    "step": 39,
                    "time_stamp": "2021-12-03 20:04:30.488188",
                    "worker_id": 3
                },
                {
                    "part_id": [
                        0,
                        3
                    ],
                    "state": "Suborder 3 complete",
                    "step": 40,
                    "time_stamp": "2021-12-03 20:04:30.488188",
                    "worker_id": 3
                },
                {
                    "part_id": [
                        0,
                        0
                    ],
                    "state": "Order 0 complete",
                    "step": 41,
                    "time_stamp": "2021-12-03 20:04:32.696505",
                    "worker_id": 0
                }
            ]
        },
        "datetime": "2021-09-14 16:15:55.421215",
        "orden": [
            {
                "ingredients": [
                    "salsa",
                    "cilantro",
                    "cebolla"
                ],
                "meat": "tripa",
                "part_id": "0-0",
                "quantity": 17,
                "status": "open",
                "type": "taco"
            },
            {
                "ingredients": [
                    "salsa",
                    "guacamole"
                ],
                "meat": "adobada",
                "part_id": "0-1",
                "quantity": 20,
                "status": "open",
                "type": "taco"
            },
            {
                "ingredients": [
                    "salsa",
                    "cebolla"
                ],
                "meat": "tripa",
                "part_id": "0-2",
                "quantity": 5,
                "status": "open",
                "type": "taco"
            },
            {
                "ingredients": [
                    "cilantro",
                    "cebolla",
                    "guacamole",
                    "salsa"
                ],
                "meat": "cabeza",
                "part_id": "0-3",
                "quantity": 2,
                "status": "open",
                "type": "taco"
            }
        ],
        "request_id": 0,
        "responsable_orden": 0,
        "status": "complete"
    },
    "1": "This index is now somewhere else, Omar will tell you where is he does not snap",
    "2": {
        "answer": {
            "end_time": 0,
            "start_time": "2021-12-03 20:02:55.685113",
            "steps": [
                {
                    "part_id": [
                        2,
                        0
                    ],
                    "state": "waiting to be cooked",
                    "step": 0,
                    "time_stamp": "2021-12-03 20:02:55.685113",
                    "worker_id": 0
                },
                {
                    "part_id": [
                        2,
                        1
                    ],
                    "state": "waiting to be cooked",
                    "step": 1,
                    "time_stamp": "2021-12-03 20:02:55.685113",
                    "worker_id": 0
                },
                {
                    "part_id": [
                        2,
                        0
                    ],
                    "state": "cooking stack #0(6) of 4.0 tacos",
                    "step": 2,
                    "time_stamp": "2021-12-03 20:03:17.968787",
                    "worker_id": 0
                },
                {
                    "part_id": [
                        2,
                        0
                    ],
                    "state": "Stack#0(6) complete",
                    "step": 3,
                    "time_stamp": "2021-12-03 20:03:28.067478",
                    "worker_id": 0
                },
                {
                    "part_id": [
                        2,
                        0
                    ],
                    "state": "Switching to order 0",
                    "step": 4,
                    "time_stamp": "2021-12-03 20:03:28.067478",
                    "worker_id": 0
                },
                {
                    "part_id": [
                        2,
                        0
                    ],
                    "state": "cooking stack #1(7) of 4.0 tacos",
                    "step": 5,
                    "time_stamp": "2021-12-03 20:03:38.216887",
                    "worker_id": 0
                },
                {
                    "part_id": [
                        2,
                        0
                    ],
                    "state": "Stack#1(7) complete",
                    "step": 6,
                    "time_stamp": "2021-12-03 20:03:48.355787",
                    "worker_id": 0
                },
                {
                    "part_id": [
                        2,
                        0
                    ],
                    "state": "Switching to order 0",
                    "step": 7,
                    "time_stamp": "2021-12-03 20:03:48.355787",
                    "worker_id": 0
                },
                {
                    "part_id": [
                        2,
                        0
                    ],
                    "state": "cooking stack #2(8) of 4.0 tacos",
                    "step": 8,
                    "time_stamp": "2021-12-03 20:03:58.542336",
                    "worker_id": 0
                },
                {
                    "part_id": [
                        2,
                        0
                    ],
                    "state": "Stack#2(8) complete",
                    "step": 9,
                    "time_stamp": "2021-12-03 20:04:08.712689",
                    "worker_id": 0
                },
                {
                    "part_id": [
                        2,
                        0
                    ],
                    "state": "Suborder 0 complete",
                    "step": 10,
                    "time_stamp": "2021-12-03 20:04:08.712689",
                    "worker_id": 0
                },
                {
                    "part_id": [
                        2,
                        0
                    ],
                    "state": "Switching to order 1",
                    "step": 11,
                    "time_stamp": "2021-12-03 20:04:08.712689",
                    "worker_id": 0
                },
                {
                    "part_id": [
                        2,
                        1
                    ],
                    "state": "cooking stack #0(9) of 3 tacos",
                    "step": 12,
                    "time_stamp": "2021-12-03 20:04:38.102075",
                    "worker_id": 0
                },
                {
                    "part_id": [
                        2,
                        1
                    ],
                    "state": "Resting",
                    "step": 13,
                    "time_stamp": "2021-12-03 20:04:39.655509",
                    "worker_id": 0
                },
                {
                    "part_id": [
                        2,
                        1
                    ],
                    "state": "fan deactivation at Omar's station",
                    "step": 14,
                    "time_stamp": "2021-12-03 20:04:56.576161",
                    "worker_id": 0
                },
                {
                    "part_id": [
                        2,
                        1
                    ],
                    "state": "Stopped resting",
                    "step": 15,
                    "time_stamp": "2021-12-03 20:05:09.655997",
                    "worker_id": 0
                },
                {
                    "part_id": [
                        2,
                        1
                    ],
                    "state": "Stack#0(9) complete",
                    "step": 16,
                    "time_stamp": "2021-12-03 20:05:12.660873",
                    "worker_id": 0
                },
                {
                    "part_id": [
                        2,
                        1
                    ],
                    "state": "Suborder 1 complete",
                    "step": 17,
                    "time_stamp": "2021-12-03 20:05:12.660873",
                    "worker_id": 0
                },
                {
                    "part_id": [
                        2,
                        0
                    ],
                    "state": "Order 2 complete",
                    "step": 18,
                    "time_stamp": "2021-12-03 20:05:12.660873",
                    "worker_id": 0
                },
                {
                    "part_id": [
                        2,
                        1
                    ],
                    "state": "Switching to order 3",
                    "step": 19,
                    "time_stamp": "2021-12-03 20:05:12.660873",
                    "worker_id": 0
                }
            ]
        },
        "datetime": "2021-09-14 17:15:55.421215",
        "orden": [
            {
                "ingredients": [
                    "guacamole",
                    "cilantro",
                    "cebolla"
                ],
                "meat": "adobada",
                "part_id": "1-0",
                "quantity": 12,
                "status": "open",
                "type": "taco"
            },
            {
                "ingredients": [
                    "cilantro"
                ],
                "meat": "adobada",
                "part_id": "1-1",
                "quantity": 3,
                "status": "open",
                "type": "taco"
            }
        ],
        "request_id": 2,
        "responsable_orden": 0,
        "status": "complete"
    },
    "3": "This index is now somewhere else, Omar will tell you where is he does not snap",
    "4": {
        "answer": {
            "end_time": 0,
            "start_time": "2021-12-03 20:02:58.701953",
            "steps": [
                {
                    "part_id": [
                        4,
                        0
                    ],
                    "state": "waiting to be cooked",
                    "step": 0,
                    "time_stamp": "2021-12-03 20:02:58.701953",
                    "worker_id": 0
                },
                {
                    "part_id": [
                        4,
                        0
                    ],
                    "state": "cooking stack #0(13) of 2 tacos",
                    "step": 1,
                    "time_stamp": "2021-12-03 20:03:03.821058",
                    "worker_id": 0
                },
                {
                    "part_id": [
                        4,
                        0
                    ],
                    "state": "Stack#0(13) complete",
                    "step": 2,
                    "time_stamp": "2021-12-03 20:03:05.839328",
                    "worker_id": 0
                },
                {
                    "part_id": [
                        4,
                        0
                    ],
                    "state": "Suborder 0 complete",
                    "step": 3,
                    "time_stamp": "2021-12-03 20:03:05.839328",
                    "worker_id": 0
                },
                {
                    "part_id": [
                        4,
                        0
                    ],
                    "state": "Order 4 complete",
                    "step": 4,
                    "time_stamp": "2021-12-03 20:03:05.839328",
                    "worker_id": 0
                },
                {
                    "part_id": [
                        4,
                        0
                    ],
                    "state": "Switching to order 7",
                    "step": 5,
                    "time_stamp": "2021-12-03 20:03:05.839328",
                    "worker_id": 0
                }
            ]
        },
        "datetime": "2021-09-14 17:15:55.421215",
        "orden": [
            {
                "ingredients": [],
                "meat": "adobada",
                "part_id": "2-0",
                "quantity": 2,
                "status": "open",
                "type": "taco"
            }
        ],
        "request_id": 4,
        "responsable_orden": 0,
        "status": "complete"
    },
    "5": "This index is now somewhere else, Omar will tell you where is he does not snap",
    "6": {
        "answer": {
            "end_time": 0,
            "start_time": "2021-12-03 20:03:01.718671",
            "steps": [
                {
                    "part_id": [
                        6,
                        0
                    ],
                    "state": "waiting to be cooked",
                    "step": 0,
                    "time_stamp": "2021-12-03 20:03:01.718671",
                    "worker_id": 0
                },
                {
                    "part_id": [
                        6,
                        1
                    ],
                    "state": "waiting to be cooked",
                    "step": 1,
                    "time_stamp": "2021-12-03 20:03:01.718671",
                    "worker_id": 0
                },
                {
                    "part_id": [
                        6,
                        1
                    ],
                    "state": "cooking stack #0(15) of 1 tacos",
                    "step": 2,
                    "time_stamp": "2021-12-03 20:03:02.788885",
                    "worker_id": 0
                },
                {
                    "part_id": [
                        6,
                        1
                    ],
                    "state": "Stack#0(15) complete",
                    "step": 3,
                    "time_stamp": "2021-12-03 20:03:03.821058",
                    "worker_id": 0
                },
                {
                    "part_id": [
                        6,
                        1
                    ],
                    "state": "Suborder 1 complete",
                    "step": 4,
                    "time_stamp": "2021-12-03 20:03:03.821058",
                    "worker_id": 0
                },
                {
                    "part_id": [
                        6,
                        1
                    ],
                    "state": "Switching to order 4",
                    "step": 5,
                    "time_stamp": "2021-12-03 20:03:03.821058",
                    "worker_id": 0
                },
                {
                    "part_id": [
                        6,
                        0
                    ],
                    "state": "Suborder 0 arrived at taquero Jerry",
                    "step": 6,
                    "time_stamp": "2021-12-03 20:03:04.744255",
                    "worker_id": 3
                },
                {
                    "part_id": [
                        6,
                        0
                    ],
                    "state": "cooking stack #0(11) of 1 tacos",
                    "step": 7,
                    "time_stamp": "2021-12-03 20:03:06.877628",
                    "worker_id": 3
                },
                {
                    "part_id": [
                        6,
                        0
                    ],
                    "state": "Stack#0(11) complete",
                    "step": 8,
                    "time_stamp": "2021-12-03 20:03:07.908993",
                    "worker_id": 3
                },
                {
                    "part_id": [
                        6,
                        0
                    ],
                    "state": "Suborder 0 complete",
                    "step": 9,
                    "time_stamp": "2021-12-03 20:03:07.908993",
                    "worker_id": 3
                },
                {
                    "part_id": [
                        6,
                        0
                    ],
                    "state": "Order 6 complete",
                    "step": 10,
                    "time_stamp": "2021-12-03 20:03:10.825505",
                    "worker_id": 0
                }
            ]
        },
        "datetime": "2021-09-14 17:15:55.421215",
        "orden": [
            {
                "ingredients": [],
                "meat": "tripa",
                "part_id": "3-0",
                "quantity": 1,
                "status": "open",
                "type": "taco"
            },
            {
                "ingredients": [],
                "meat": "adobada",
                "part_id": "3-1",
                "quantity": 1,
                "status": "open",
                "type": "taco"
            }
        ],
        "request_id": 6,
        "responsable_orden": 0,
        "status": "complete"
    },
    "7": "This index is now somewhere else, Omar will tell you where is he does not snap",
    "8": {
        "answer": {
            "end_time": 0,
            "start_time": "2021-12-03 20:03:04.744255",
            "steps": [
                {
                    "part_id": [
                        8,
                        0
                    ],
                    "state": "waiting to be cooked",
                    "step": 0,
                    "time_stamp": "2021-12-03 20:03:04.744255",
                    "worker_id": 0
                },
                {
                    "part_id": [
                        8,
                        1
                    ],
                    "state": "waiting to be cooked",
                    "step": 1,
                    "time_stamp": "2021-12-03 20:03:04.744255",
                    "worker_id": 0
                },
                {
                    "part_id": [
                        8,
                        2
                    ],
                    "state": "waiting to be cooked",
                    "step": 2,
                    "time_stamp": "2021-12-03 20:03:04.744255",
                    "worker_id": 0
                },
                {
                    "part_id": [
                        8,
                        0
                    ],
                    "state": "Suborder 0 arrived at taquero Jerry",
                    "step": 3,
                    "time_stamp": "2021-12-03 20:03:07.798429",
                    "worker_id": 3
                },
                {
                    "part_id": [
                        8,
                        1
                    ],
                    "state": "Suborder 1 arrived at taquero Jerry",
                    "step": 4,
                    "time_stamp": "2021-12-03 20:03:10.825505",
                    "worker_id": 3
                },
                {
                    "part_id": [
                        8,
                        2
                    ],
                    "state": "Suborder 2 arrived at taquero Jerry",
                    "step": 5,
                    "time_stamp": "2021-12-03 20:03:13.874060",
                    "worker_id": 3
                },
                {
                    "part_id": [
                        8,
                        1
                    ],
                    "state": "cooking stack #0(14) of 3 tacos",
                    "step": 6,
                    "time_stamp": "2021-12-03 20:05:15.679409",
                    "worker_id": 3
                },
                {
                    "part_id": [
                        8,
                        1
                    ],
                    "state": "Stack#0(14) complete",
                    "step": 7,
                    "time_stamp": "2021-12-03 20:05:20.252665",
                    "worker_id": 3
                },
                {
                    "part_id": [
                        8,
                        1
                    ],
                    "state": "Suborder 1 complete",
                    "step": 8,
                    "time_stamp": "2021-12-03 20:05:20.252665",
                    "worker_id": 3
                },
                {
                    "part_id": [
                        8,
                        2
                    ],
                    "state": "cooking stack #0(15) of 2 tacos",
                    "step": 9,
                    "time_stamp": "2021-12-03 20:05:20.252665",
                    "worker_id": 3
                },
                {
                    "part_id": [
                        8,
                        0
                    ],
                    "state": "Order 8 complete",
                    "step": 10,
                    "time_stamp": "2021-12-03 20:05:21.221679",
                    "worker_id": 0
                },
                {
                    "part_id": [
                        8,
                        2
                    ],
                    "state": "Stack#0(15) complete",
                    "step": 11,
                    "time_stamp": "2021-12-03 20:05:24.271697",
                    "worker_id": 3
                },
                {
                    "part_id": [
                        8,
                        2
                    ],
                    "state": "Suborder 2 complete",
                    "step": 12,
                    "time_stamp": "2021-12-03 20:05:24.271697",
                    "worker_id": 3
                },
                {
                    "part_id": [
                        8,
                        0
                    ],
                    "state": "Order 8 complete",
                    "step": 13,
                    "time_stamp": "2021-12-03 20:05:27.273783",
                    "worker_id": 0
                },
                {
                    "part_id": [
                        8,
                        0
                    ],
                    "state": "cooking stack #0(13) of 5 tacos",
                    "step": 14,
                    "time_stamp": "2021-12-03 20:05:28.827905",
                    "worker_id": 3
                },
                {
                    "part_id": [
                        8,
                        0
                    ],
                    "state": "Stack#0(13) complete",
                    "step": 15,
                    "time_stamp": "2021-12-03 20:05:33.904821",
                    "worker_id": 3
                },
                {
                    "part_id": [
                        8,
                        0
                    ],
                    "state": "Suborder 0 complete",
                    "step": 16,
                    "time_stamp": "2021-12-03 20:05:33.904821",
                    "worker_id": 3
                },
                {
                    "part_id": [
                        8,
                        0
                    ],
                    "state": "Order 8 complete",
                    "step": 17,
                    "time_stamp": "2021-12-03 20:05:36.703934",
                    "worker_id": 0
                }
            ]
        },
        "datetime": "2021-09-14 17:15:55.421215",
        "orden": [
            {
                "ingredients": [],
                "meat": "cabeza",
                "part_id": "4-0",
                "quantity": 5,
                "status": "open",
                "type": "taco"
            },
            {
                "ingredients": [
                    "guacamole"
                ],
                "meat": "tripa",
                "part_id": "4-1",
                "quantity": 3,
                "status": "open",
                "type": "taco"
            },
            {
                "ingredients": [
                    "guacamole",
                    "cilantro"
                ],
                "meat": "tripa",
                "part_id": "4-2",
                "quantity": 2,
                "status": "open",
                "type": "taco"
            }
        ],
        "request_id": 8,
        "responsable_orden": 0,
        "status": "complete"
    },
    "9": {
        "answer": {
            "end_time": 0,
            "start_time": "2021-12-03 20:03:07.798429",
            "steps": [
                {
                    "part_id": [
                        9,
                        0
                    ],
                    "state": "waiting to be cooked",
                    "step": 0,
                    "time_stamp": "2021-12-03 20:03:07.798429",
                    "worker_id": 0
                },
                {
                    "part_id": [
                        9,
                        1
                    ],
                    "state": "waiting to be cooked",
                    "step": 1,
                    "time_stamp": "2021-12-03 20:03:07.798429",
                    "worker_id": 0
                },
                {
                    "part_id": [
                        9,
                        1
                    ],
                    "state": "cooking stack #0(19) of 2 tacos",
                    "step": 2,
                    "time_stamp": "2021-12-03 20:04:16.287848",
                    "worker_id": 0
                },
                {
                    "part_id": [
                        9,
                        1
                    ],
                    "state": "Stack#0(19) complete",
                    "step": 3,
                    "time_stamp": "2021-12-03 20:04:21.360413",
                    "worker_id": 0
                },
                {
                    "part_id": [
                        9,
                        1
                    ],
                    "state": "Suborder 1 complete",
                    "step": 4,
                    "time_stamp": "2021-12-03 20:04:21.360413",
                    "worker_id": 0
                },
                {
                    "part_id": [
                        9,
                        1
                    ],
                    "state": "Switching to order 1",
                    "step": 5,
                    "time_stamp": "2021-12-03 20:04:21.360413",
                    "worker_id": 0
                },
                {
                    "part_id": [
                        9,
                        0
                    ],
                    "state": "cooking stack #0(17) of 2 tacos",
                    "step": 6,
                    "time_stamp": "2021-12-03 20:05:22.770149",
                    "worker_id": 0
                },
                {
                    "part_id": [
                        9,
                        0
                    ],
                    "state": "Stack#0(17) complete",
                    "step": 7,
                    "time_stamp": "2021-12-03 20:05:26.826649",
                    "worker_id": 0
                },
                {
                    "part_id": [
                        9,
                        0
                    ],
                    "state": "Switching to order 3",
                    "step": 8,
                    "time_stamp": "2021-12-03 20:05:26.826649",
                    "worker_id": 0
                },
                {
                    "part_id": [
                        9,
                        0
                    ],
                    "state": "cooking stack #1(18) of 8 tacos",
                    "step": 9,
                    "time_stamp": "2021-12-03 20:05:37.162624",
                    "worker_id": 0
                },
                {
                    "part_id": [
                        9,
                        0
                    ],
                    "state": "Stack#1(18) complete",
                    "step": 10,
                    "time_stamp": "2021-12-03 20:05:53.744681",
                    "worker_id": 0
                },
                {
                    "part_id": [
                        9,
                        0
                    ],
                    "state": "Suborder 0 complete",
                    "step": 11,
                    "time_stamp": "2021-12-03 20:05:53.744681",
                    "worker_id": 0
                },
                {
                    "part_id": [
                        9,
                        0
                    ],
                    "state": "Order 9 complete",
                    "step": 12,
                    "time_stamp": "2021-12-03 20:05:53.744681",
                    "worker_id": 0
                },
                {
                    "part_id": [
                        9,
                        0
                    ],
                    "state": "Switching to order 5",
                    "step": 13,
                    "time_stamp": "2021-12-03 20:05:53.745678",
                    "worker_id": 0
                }
            ]
        },
        "datetime": "2021-09-14 17:15:55.421215",
        "orden": [
            {
                "ingredients": [
                    "cilantro",
                    "cebolla"
                ],
                "meat": "adobada",
                "part_id": "5-0",
                "quantity": 10,
                "status": "open",
                "type": "taco"
            },
            {
                "ingredients": [
                    "guacamole",
                    "salsa",
                    "cilantro"
                ],
                "meat": "adobada",
                "part_id": "5-1",
                "quantity": 2,
                "status": "open",
                "type": "taco"
            }
        ],
        "request_id": 9,
        "responsable_orden": 0,
        "status": "complete"
    }
}